vnpy_ctastrategy/__init__.py
vnpy_ctastrategy/backtesting.py
vnpy_ctastrategy/base.py
vnpy_ctastrategy/engine.py
vnpy_ctastrategy/template.py
vnpy_ctastrategy/locale/__init__.py
vnpy_ctastrategy/locale/build_hook.py
vnpy_ctastrategy/locale/generate_mo.bat
vnpy_ctastrategy/locale/generate_pot.bat
vnpy_ctastrategy/locale/vnpy_ctastrategy.pot
vnpy_ctastrategy/locale/en/LC_MESSAGES/vnpy_ctastrategy.po
vnpy_ctastrategy/strategies/__init__.py
vnpy_ctastrategy/strategies/atr_rsi_strategy.py
vnpy_ctastrategy/strategies/boll_channel_strategy.py
vnpy_ctastrategy/strategies/double_ma_strategy.py
vnpy_ctastrategy/strategies/dual_thrust_strategy.py
vnpy_ctastrategy/strategies/king_keltner_strategy.py
vnpy_ctastrategy/strategies/multi_signal_strategy.py
vnpy_ctastrategy/strategies/multi_timeframe_strategy.py
vnpy_ctastrategy/strategies/test_strategy.py
vnpy_ctastrategy/strategies/turtle_signal_strategy.py
vnpy_ctastrategy/ui/__init__.py
vnpy_ctastrategy/ui/cta.ico
vnpy_ctastrategy/ui/rollover.py
vnpy_ctastrategy/ui/widget.py
vnpy_ctastrategy/locale/en/LC_MESSAGES/vnpy_ctastrategy.mo
vnpy_ctastrategy-1.4.1.dist-info/METADATA
vnpy_ctastrategy-1.4.1.dist-info/WHEEL
vnpy_ctastrategy-1.4.1.dist-info/licenses/LICENSE
vnpy_ctastrategy-1.4.1.dist-info/RECORD
